strslice/__init__.py
strslice/compat.py
strslice/constants.py
strslice/generator.py
strslice/grapheme.py
strslice/slice.py
strslice/tests.py
strslice/gen/__init__.py
strslice/gen/grapheme_break_properties.py
strslice-1.0.dist-info/DESCRIPTION.rst
strslice-1.0.dist-info/METADATA
strslice-1.0.dist-info/RECORD
strslice-1.0.dist-info/WHEEL
strslice-1.0.dist-info/entry_points.txt
strslice-1.0.dist-info/metadata.json
strslice-1.0.dist-info/top_level.txt
