Metadata-Version: 2.0
Name: strslice
Version: 1.0
Summary: Python 3 style emoji-safe string slicing for Python 2.
Home-page: https://github.com/ojii/strslice
Author: Jonas Obrist
Author-email: ojiidotch@gmail.com
License: MIT
Platform: UNKNOWN
Classifier: License :: OSI Approved :: MIT License
Classifier: Programming Language :: Python :: 2.7
Classifier: Development Status :: 5 - Production/Stable
Classifier: Intended Audience :: Developers
Classifier: Topic :: Text Processing
Requires-Dist: jinja2
Requires-Dist: requests
